common/__init__.py
common/runtime_stats.py
file_utils/__init__.py
file_utils/files.py
str_utils/__init__.py
str_utils/str_utils.py
aurora_common_utils-0.1.2.dist-info/LICENSE
aurora_common_utils-0.1.2.dist-info/METADATA
aurora_common_utils-0.1.2.dist-info/WHEEL
aurora_common_utils-0.1.2.dist-info/top_level.txt
aurora_common_utils-0.1.2.dist-info/RECORD
