Metadata-Version: 2.1
Name: aurora-common-utils
Version: 0.1.2
Summary: File operations utils.
Home-page: https://github.com/
Author: xblia
Author-email: worldandyou@163.com
License: UNKNOWN
Platform: UNKNOWN
Classifier: Programming Language :: Python :: 3
Classifier: License :: OSI Approved :: MIT License
Classifier: Operating System :: OS Independent
Requires-Python: >=3.6
